alibabacloud_eflo_controller20221215/__init__.py
alibabacloud_eflo_controller20221215/client.py
alibabacloud_eflo_controller20221215/models/__init__.py
alibabacloud_eflo_controller20221215/models/_approve_operation_request.py
alibabacloud_eflo_controller20221215/models/_approve_operation_response.py
alibabacloud_eflo_controller20221215/models/_approve_operation_response_body.py
alibabacloud_eflo_controller20221215/models/_change_node_group_request.py
alibabacloud_eflo_controller20221215/models/_change_node_group_response.py
alibabacloud_eflo_controller20221215/models/_change_node_group_response_body.py
alibabacloud_eflo_controller20221215/models/_change_node_group_shrink_request.py
alibabacloud_eflo_controller20221215/models/_change_node_types_request.py
alibabacloud_eflo_controller20221215/models/_change_node_types_response.py
alibabacloud_eflo_controller20221215/models/_change_node_types_response_body.py
alibabacloud_eflo_controller20221215/models/_change_node_types_shrink_request.py
alibabacloud_eflo_controller20221215/models/_change_resource_group_request.py
alibabacloud_eflo_controller20221215/models/_change_resource_group_response.py
alibabacloud_eflo_controller20221215/models/_change_resource_group_response_body.py
alibabacloud_eflo_controller20221215/models/_close_session_request.py
alibabacloud_eflo_controller20221215/models/_close_session_response.py
alibabacloud_eflo_controller20221215/models/_close_session_response_body.py
alibabacloud_eflo_controller20221215/models/_create_cluster_request.py
alibabacloud_eflo_controller20221215/models/_create_cluster_response.py
alibabacloud_eflo_controller20221215/models/_create_cluster_response_body.py
alibabacloud_eflo_controller20221215/models/_create_cluster_shrink_request.py
alibabacloud_eflo_controller20221215/models/_create_diagnostic_task_request.py
alibabacloud_eflo_controller20221215/models/_create_diagnostic_task_response.py
alibabacloud_eflo_controller20221215-3.0.2.dist-info/LICENSE
alibabacloud_eflo_controller20221215-3.0.2.dist-info/METADATA
alibabacloud_eflo_controller20221215-3.0.2.dist-info/WHEEL
alibabacloud_eflo_controller20221215-3.0.2.dist-info/top_level.txt
alibabacloud_eflo_controller20221215-3.0.2.dist-info/RECORD
